lotusrpc-0.9.7.dist-info/licenses/LICENSE
lrpc/__init__.py
lrpc/lrpcc.py
lrpc/lrpcg.py
lrpc/py.typed
lrpc/client/__init__.py
lrpc/client/client_cli_visitor.py
lrpc/client/decoder.py
lrpc/client/encoder.py
lrpc/client/lrpc_client.py
lrpc/client/transport.py
lrpc/codegen/__init__.py
lrpc/codegen/common.py
lrpc/codegen/constants.py
lrpc/codegen/enum.py
lrpc/codegen/meta.py
lrpc/codegen/server_include.py
lrpc/codegen/service_include.py
lrpc/codegen/service_shim.py
lrpc/codegen/struct.py
lrpc/codegen/utils.py
lrpc/core/__init__.py
lrpc/core/constant.py
lrpc/core/definition.py
lrpc/core/enum.py
lrpc/core/function.py
lrpc/core/service.py
lrpc/core/stream.py
lrpc/core/struct.py
lrpc/core/var.py
lrpc/plugins/__init__.py
lrpc/plugins/lrpcc_serial.py
lrpc/resources/__init__.py
lrpc/resources/cpp/EtlRwExtensions.hpp
lrpc/resources/cpp/Server.hpp
lrpc/resources/cpp/Service.hpp
lrpc/resources/cpp/__init__.py
lrpc/resources/cpp/export.py
lrpc/schema/__init__.py
lrpc/schema/load.py
lrpc/schema/lotusrpc-schema.json
lrpc/types/__init__.py
lrpc/types/lrpc_type.py
lrpc/utils/__init__.py
lrpc/utils/load_definition.py
lrpc/validation/__init__.py
lrpc/validation/custom_types.py
lrpc/validation/enum.py
lrpc/validation/function_and_stream.py
lrpc/validation/names.py
lrpc/validation/param_and_return.py
lrpc/validation/semantic_analyzer.py
lrpc/validation/service.py
lrpc/validation/struct.py
lrpc/validation/validator.py
lrpc/visitors/__init__.py
lrpc/visitors/lrpc_visitor.py
lrpc/visitors/puml_visitor.py
lotusrpc-0.9.7.dist-info/METADATA
lotusrpc-0.9.7.dist-info/WHEEL
lotusrpc-0.9.7.dist-info/entry_points.txt
lotusrpc-0.9.7.dist-info/top_level.txt
lotusrpc-0.9.7.dist-info/RECORD
