Metadata-Version: 2.4
Name: lotusrpc
Version: 0.9.7
Summary: A code generator for remote procedure calls on embedded systems
Author: T Zijnge
License: MIT License
Project-URL: homepage, https://github.com/tzijnge/LotusRpc
Project-URL: Bug Tracker, https://github.com/tzijnge/LotusRpc/issues
Project-URL: Documentation, https://tzijnge.github.io/LotusRpc/
Project-URL: Source Code, https://github.com/tzijnge/LotusRpc
Keywords: code generation,embedded systems,C++,RPC,remote procedure call
Classifier: Development Status :: 3 - Alpha
Classifier: Intended Audience :: Developers
Classifier: License :: OSI Approved :: MIT License
Classifier: Operating System :: OS Independent
Classifier: Programming Language :: Python :: 3
Classifier: Programming Language :: C++
Classifier: Topic :: Software Development :: Code Generators
Classifier: Topic :: Software Development :: Embedded Systems
Requires-Python: >=3.10
License-File: LICENSE
Requires-Dist: code-generation==2.3.0
Requires-Dist: pyyaml==6.0.2
Requires-Dist: jsonschema==4.25.0
Requires-Dist: click==8.3.0
Requires-Dist: typing-extensions==4.15.0
Requires-Dist: colorama==0.4.6
Provides-Extra: serial
Requires-Dist: pyserial==3.5; extra == "serial"
Dynamic: license-file
